.coveragerc
.dockerignore
AUTHORS
ChangeLog
Dockerfile
LICENSE
MANIFEST.in
Makefile
PKG-INFO
README.rst
requirements.txt
setup.cfg
setup.py
test-requirements.txt
tox.ini
bin/github2gitlab
github2gitlab/__init__.py
github2gitlab/main.py
hub2lab.egg-info/PKG-INFO
hub2lab.egg-info/SOURCES.txt
hub2lab.egg-info/dependency_links.txt
hub2lab.egg-info/requires.txt
hub2lab.egg-info/top_level.txt
tests/integration.py
tests/setup-gitlab.sh
tests/test_github2gitlab.py