Metadata-Version: 1.1
Name: hub2lab
Version: 1.6.0
Summary: command line tool to migrate projects from GitHub to GitLab
Home-page: https://github.com/ubc/github2gitlab
Author: Pan Luo
Author-email: pan.luo@ubc.ca
License: UNKNOWN
Platform: UNKNOWN
Classifier: Environment :: No Input/Output (Daemon)
Classifier: Intended Audience :: Information Technology
Classifier: Intended Audience :: System Administrators
Classifier: Operating System :: POSIX :: Linux
Classifier: License :: OSI Approved :: GNU Affero General Public License v3 or later (AGPLv3+)
Classifier: Programming Language :: Python
Classifier: Programming Language :: Python :: 2.7
Classifier: Topic :: Utilities
